brightspot_employee/__init__.py
brightspot_employee/employee.py
brightspot_employee/room.py
brightspot_employee/util.py
brightspot_employee-0.1.0.dist-info/LICENSE
brightspot_employee-0.1.0.dist-info/METADATA
brightspot_employee-0.1.0.dist-info/WHEEL
brightspot_employee-0.1.0.dist-info/top_level.txt
brightspot_employee-0.1.0.dist-info/RECORD
